{
  "updated_at": "2026-06-29 10:49:50",
  "source": {
    "groups": "https://worldcup26.ir/get/groups",
    "teams": "data\\teams.json"
  },
  "groups": {
    "A": [
      {
        "team_id": "1",
        "team": "Mexico",
        "fifa_code": "MEX",
        "flag": "https://flagcdn.com/w80/mx.png",
        "played": 3,
        "wins": 3,
        "draws": 0,
        "losses": 0,
        "points": 9,
        "goals_for": 6,
        "goals_against": 0,
        "goal_difference": 6,
        "position": 1
      },
      {
        "team_id": "2",
        "team": "South Africa",
        "fifa_code": "RSA",
        "flag": "https://flagcdn.com/w80/za.png",
        "played": 3,
        "wins": 1,
        "draws": 1,
        "losses": 1,
        "points": 4,
        "goals_for": 2,
        "goals_against": 3,
        "goal_difference": -1,
        "position": 2
      },
      {
        "team_id": "3",
        "team": "South Korea",
        "fifa_code": "KOR",
        "flag": "https://flagcdn.com/w80/kr.png",
        "played": 3,
        "wins": 1,
        "draws": 0,
        "losses": 2,
        "points": 3,
        "goals_for": 2,
        "goals_against": 3,
        "goal_difference": -1,
        "position": 3
      },
      {
        "team_id": "4",
        "team": "Czech Republic",
        "fifa_code": "CZE",
        "flag": "https://flagcdn.com/w80/cz.png",
        "played": 3,
        "wins": 0,
        "draws": 1,
        "losses": 2,
        "points": 1,
        "goals_for": 2,
        "goals_against": 6,
        "goal_difference": -4,
        "position": 4
      }
    ],
    "B": [
      {
        "team_id": "8",
        "team": "Switzerland",
        "fifa_code": "SUI",
        "flag": "https://flagcdn.com/w80/ch.png",
        "played": 3,
        "wins": 2,
        "draws": 1,
        "losses": 0,
        "points": 7,
        "goals_for": 7,
        "goals_against": 3,
        "goal_difference": 4,
        "position": 1
      },
      {
        "team_id": "5",
        "team": "Canada",
        "fifa_code": "CAN",
        "flag": "https://flagcdn.com/w80/ca.png",
        "played": 3,
        "wins": 1,
        "draws": 1,
        "losses": 1,
        "points": 4,
        "goals_for": 8,
        "goals_against": 3,
        "goal_difference": 5,
        "position": 2
      },
      {
        "team_id": "6",
        "team": "Bosnia and Herzegovina",
        "fifa_code": "BIH",
        "flag": "https://flagcdn.com/w80/ba.png",
        "played": 3,
        "wins": 1,
        "draws": 1,
        "losses": 1,
        "points": 4,
        "goals_for": 5,
        "goals_against": 6,
        "goal_difference": -1,
        "position": 3
      },
      {
        "team_id": "7",
        "team": "Qatar",
        "fifa_code": "QAT",
        "flag": "https://flagcdn.com/w80/qa.png",
        "played": 3,
        "wins": 0,
        "draws": 1,
        "losses": 2,
        "points": 1,
        "goals_for": 2,
        "goals_against": 10,
        "goal_difference": -8,
        "position": 4
      }
    ],
    "C": [
      {
        "team_id": "9",
        "team": "Brazil",
        "fifa_code": "BRA",
        "flag": "https://flagcdn.com/w80/br.png",
        "played": 3,
        "wins": 2,
        "draws": 1,
        "losses": 0,
        "points": 7,
        "goals_for": 7,
        "goals_against": 1,
        "goal_difference": 6,
        "position": 1
      },
      {
        "team_id": "10",
        "team": "Morocco",
        "fifa_code": "MAR",
        "flag": "https://flagcdn.com/w80/ma.png",
        "played": 3,
        "wins": 2,
        "draws": 1,
        "losses": 0,
        "points": 7,
        "goals_for": 6,
        "goals_against": 3,
        "goal_difference": 3,
        "position": 2
      },
      {
        "team_id": "12",
        "team": "Scotland",
        "fifa_code": "SCO",
        "flag": "https://flagcdn.com/w80/gb-sct.png",
        "played": 3,
        "wins": 1,
        "draws": 0,
        "losses": 2,
        "points": 3,
        "goals_for": 1,
        "goals_against": 4,
        "goal_difference": -3,
        "position": 3
      },
      {
        "team_id": "11",
        "team": "Haiti",
        "fifa_code": "HAI",
        "flag": "https://flagcdn.com/w80/ht.png",
        "played": 3,
        "wins": 0,
        "draws": 0,
        "losses": 3,
        "points": 0,
        "goals_for": 2,
        "goals_against": 8,
        "goal_difference": -6,
        "position": 4
      }
    ],
    "D": [
      {
        "team_id": "13",
        "team": "United States",
        "fifa_code": "USA",
        "flag": "https://flagcdn.com/w80/us.png",
        "played": 3,
        "wins": 2,
        "draws": 0,
        "losses": 1,
        "points": 6,
        "goals_for": 8,
        "goals_against": 4,
        "goal_difference": 4,
        "position": 1
      },
      {
        "team_id": "15",
        "team": "Australia",
        "fifa_code": "AUS",
        "flag": "https://flagcdn.com/w80/au.png",
        "played": 3,
        "wins": 1,
        "draws": 1,
        "losses": 1,
        "points": 4,
        "goals_for": 2,
        "goals_against": 2,
        "goal_difference": 0,
        "position": 2
      },
      {
        "team_id": "14",
        "team": "Paraguay",
        "fifa_code": "PAR",
        "flag": "https://flagcdn.com/w80/py.png",
        "played": 3,
        "wins": 1,
        "draws": 1,
        "losses": 1,
        "points": 4,
        "goals_for": 2,
        "goals_against": 4,
        "goal_difference": -2,
        "position": 3
      },
      {
        "team_id": "16",
        "team": "Turkey",
        "fifa_code": "TUR",
        "flag": "https://flagcdn.com/w80/tr.png",
        "played": 3,
        "wins": 1,
        "draws": 0,
        "losses": 2,
        "points": 3,
        "goals_for": 3,
        "goals_against": 5,
        "goal_difference": -2,
        "position": 4
      }
    ],
    "E": [
      {
        "team_id": "17",
        "team": "Germany",
        "fifa_code": "GER",
        "flag": "https://flagcdn.com/w80/de.png",
        "played": 3,
        "wins": 2,
        "draws": 0,
        "losses": 1,
        "points": 6,
        "goals_for": 10,
        "goals_against": 4,
        "goal_difference": 6,
        "position": 1
      },
      {
        "team_id": "19",
        "team": "Ivory Coast",
        "fifa_code": "CIV",
        "flag": "https://flagcdn.com/w80/ci.png",
        "played": 3,
        "wins": 2,
        "draws": 0,
        "losses": 1,
        "points": 6,
        "goals_for": 4,
        "goals_against": 2,
        "goal_difference": 2,
        "position": 2
      },
      {
        "team_id": "20",
        "team": "Ecuador",
        "fifa_code": "ECU",
        "flag": "https://flagcdn.com/w80/ec.png",
        "played": 3,
        "wins": 1,
        "draws": 1,
        "losses": 1,
        "points": 4,
        "goals_for": 2,
        "goals_against": 2,
        "goal_difference": 0,
        "position": 3
      },
      {
        "team_id": "18",
        "team": "Curaçao",
        "fifa_code": "CUW",
        "flag": "https://flagcdn.com/w80/cw.png",
        "played": 3,
        "wins": 0,
        "draws": 1,
        "losses": 2,
        "points": 1,
        "goals_for": 1,
        "goals_against": 9,
        "goal_difference": -8,
        "position": 4
      }
    ],
    "F": [
      {
        "team_id": "21",
        "team": "Netherlands",
        "fifa_code": "NED",
        "flag": "https://flagcdn.com/w80/nl.png",
        "played": 3,
        "wins": 2,
        "draws": 1,
        "losses": 0,
        "points": 7,
        "goals_for": 10,
        "goals_against": 4,
        "goal_difference": 6,
        "position": 1
      },
      {
        "team_id": "22",
        "team": "Japan",
        "fifa_code": "JPN",
        "flag": "https://flagcdn.com/w80/jp.png",
        "played": 3,
        "wins": 1,
        "draws": 2,
        "losses": 0,
        "points": 5,
        "goals_for": 7,
        "goals_against": 3,
        "goal_difference": 4,
        "position": 2
      },
      {
        "team_id": "23",
        "team": "Sweden",
        "fifa_code": "SWE",
        "flag": "https://flagcdn.com/w80/se.png",
        "played": 3,
        "wins": 1,
        "draws": 1,
        "losses": 1,
        "points": 4,
        "goals_for": 7,
        "goals_against": 7,
        "goal_difference": 0,
        "position": 3
      },
      {
        "team_id": "24",
        "team": "Tunisia",
        "fifa_code": "TUN",
        "flag": "https://flagcdn.com/w80/tn.png",
        "played": 3,
        "wins": 0,
        "draws": 0,
        "losses": 3,
        "points": 0,
        "goals_for": 2,
        "goals_against": 12,
        "goal_difference": -10,
        "position": 4
      }
    ],
    "G": [
      {
        "team_id": "25",
        "team": "Belgium",
        "fifa_code": "BEL",
        "flag": "https://flagcdn.com/w80/be.png",
        "played": 3,
        "wins": 1,
        "draws": 2,
        "losses": 0,
        "points": 5,
        "goals_for": 6,
        "goals_against": 2,
        "goal_difference": 4,
        "position": 1
      },
      {
        "team_id": "26",
        "team": "Egypt",
        "fifa_code": "EGY",
        "flag": "https://flagcdn.com/w80/eg.png",
        "played": 3,
        "wins": 1,
        "draws": 2,
        "losses": 0,
        "points": 5,
        "goals_for": 5,
        "goals_against": 3,
        "goal_difference": 2,
        "position": 2
      },
      {
        "team_id": "27",
        "team": "Iran",
        "fifa_code": "IRN",
        "flag": "https://flagcdn.com/w80/ir.png",
        "played": 3,
        "wins": 0,
        "draws": 3,
        "losses": 0,
        "points": 3,
        "goals_for": 3,
        "goals_against": 3,
        "goal_difference": 0,
        "position": 3
      },
      {
        "team_id": "28",
        "team": "New Zealand",
        "fifa_code": "NZL",
        "flag": "https://flagcdn.com/w80/nz.png",
        "played": 3,
        "wins": 0,
        "draws": 1,
        "losses": 2,
        "points": 1,
        "goals_for": 4,
        "goals_against": 10,
        "goal_difference": -6,
        "position": 4
      }
    ],
    "H": [
      {
        "team_id": "29",
        "team": "Spain",
        "fifa_code": "ESP",
        "flag": "https://flagcdn.com/w80/es.png",
        "played": 3,
        "wins": 2,
        "draws": 1,
        "losses": 0,
        "points": 7,
        "goals_for": 5,
        "goals_against": 0,
        "goal_difference": 5,
        "position": 1
      },
      {
        "team_id": "30",
        "team": "Cape Verde",
        "fifa_code": "CPV",
        "flag": "https://flagcdn.com/w80/cv.png",
        "played": 3,
        "wins": 0,
        "draws": 3,
        "losses": 0,
        "points": 3,
        "goals_for": 2,
        "goals_against": 2,
        "goal_difference": 0,
        "position": 2
      },
      {
        "team_id": "32",
        "team": "Uruguay",
        "fifa_code": "URU",
        "flag": "https://flagcdn.com/w80/uy.png",
        "played": 3,
        "wins": 0,
        "draws": 2,
        "losses": 1,
        "points": 2,
        "goals_for": 3,
        "goals_against": 4,
        "goal_difference": -1,
        "position": 3
      },
      {
        "team_id": "31",
        "team": "Saudi Arabia",
        "fifa_code": "KSA",
        "flag": "https://flagcdn.com/w80/sa.png",
        "played": 3,
        "wins": 0,
        "draws": 2,
        "losses": 1,
        "points": 2,
        "goals_for": 1,
        "goals_against": 5,
        "goal_difference": -4,
        "position": 4
      }
    ],
    "I": [
      {
        "team_id": "33",
        "team": "France",
        "fifa_code": "FRA",
        "flag": "https://flagcdn.com/w80/fr.png",
        "played": 3,
        "wins": 3,
        "draws": 0,
        "losses": 0,
        "points": 9,
        "goals_for": 10,
        "goals_against": 2,
        "goal_difference": 8,
        "position": 1
      },
      {
        "team_id": "36",
        "team": "Norway",
        "fifa_code": "NOR",
        "flag": "https://flagcdn.com/w80/no.png",
        "played": 3,
        "wins": 2,
        "draws": 0,
        "losses": 1,
        "points": 6,
        "goals_for": 8,
        "goals_against": 7,
        "goal_difference": 1,
        "position": 2
      },
      {
        "team_id": "34",
        "team": "Senegal",
        "fifa_code": "SEN",
        "flag": "https://flagcdn.com/w80/sn.png",
        "played": 3,
        "wins": 1,
        "draws": 0,
        "losses": 2,
        "points": 3,
        "goals_for": 8,
        "goals_against": 6,
        "goal_difference": 2,
        "position": 3
      },
      {
        "team_id": "35",
        "team": "Iraq",
        "fifa_code": "IRQ",
        "flag": "https://flagcdn.com/w80/iq.png",
        "played": 3,
        "wins": 0,
        "draws": 0,
        "losses": 3,
        "points": 0,
        "goals_for": 1,
        "goals_against": 12,
        "goal_difference": -11,
        "position": 4
      }
    ],
    "J": [
      {
        "team_id": "37",
        "team": "Argentina",
        "fifa_code": "ARG",
        "flag": "https://flagcdn.com/w80/ar.png",
        "played": 3,
        "wins": 3,
        "draws": 0,
        "losses": 0,
        "points": 9,
        "goals_for": 8,
        "goals_against": 1,
        "goal_difference": 7,
        "position": 1
      },
      {
        "team_id": "39",
        "team": "Austria",
        "fifa_code": "AUT",
        "flag": "https://flagcdn.com/w80/at.png",
        "played": 3,
        "wins": 1,
        "draws": 1,
        "losses": 1,
        "points": 4,
        "goals_for": 6,
        "goals_against": 6,
        "goal_difference": 0,
        "position": 2
      },
      {
        "team_id": "38",
        "team": "Algeria",
        "fifa_code": "ALG",
        "flag": "https://flagcdn.com/w80/dz.png",
        "played": 3,
        "wins": 1,
        "draws": 1,
        "losses": 1,
        "points": 4,
        "goals_for": 5,
        "goals_against": 7,
        "goal_difference": -2,
        "position": 3
      },
      {
        "team_id": "40",
        "team": "Jordan",
        "fifa_code": "JOR",
        "flag": "https://flagcdn.com/w80/jo.png",
        "played": 3,
        "wins": 0,
        "draws": 0,
        "losses": 3,
        "points": 0,
        "goals_for": 3,
        "goals_against": 8,
        "goal_difference": -5,
        "position": 4
      }
    ],
    "K": [
      {
        "team_id": "44",
        "team": "Colombia",
        "fifa_code": "COL",
        "flag": "https://flagcdn.com/w80/co.png",
        "played": 3,
        "wins": 2,
        "draws": 1,
        "losses": 0,
        "points": 7,
        "goals_for": 4,
        "goals_against": 1,
        "goal_difference": 3,
        "position": 1
      },
      {
        "team_id": "41",
        "team": "Portugal",
        "fifa_code": "POR",
        "flag": "https://flagcdn.com/w80/pt.png",
        "played": 3,
        "wins": 1,
        "draws": 2,
        "losses": 0,
        "points": 5,
        "goals_for": 6,
        "goals_against": 1,
        "goal_difference": 5,
        "position": 2
      },
      {
        "team_id": "42",
        "team": "Democratic Republic of the Congo",
        "fifa_code": "COD",
        "flag": "https://flagcdn.com/w80/cd.png",
        "played": 3,
        "wins": 1,
        "draws": 1,
        "losses": 1,
        "points": 4,
        "goals_for": 4,
        "goals_against": 3,
        "goal_difference": 1,
        "position": 3
      },
      {
        "team_id": "43",
        "team": "Uzbekistan",
        "fifa_code": "UZB",
        "flag": "https://flagcdn.com/w80/uz.png",
        "played": 3,
        "wins": 0,
        "draws": 0,
        "losses": 3,
        "points": 0,
        "goals_for": 2,
        "goals_against": 11,
        "goal_difference": -9,
        "position": 4
      }
    ],
    "L": [
      {
        "team_id": "45",
        "team": "England",
        "fifa_code": "ENG",
        "flag": "https://flagcdn.com/w80/gb-eng.png",
        "played": 3,
        "wins": 2,
        "draws": 1,
        "losses": 0,
        "points": 7,
        "goals_for": 6,
        "goals_against": 2,
        "goal_difference": 4,
        "position": 1
      },
      {
        "team_id": "46",
        "team": "Croatia",
        "fifa_code": "CRO",
        "flag": "https://flagcdn.com/w80/hr.png",
        "played": 3,
        "wins": 2,
        "draws": 0,
        "losses": 1,
        "points": 6,
        "goals_for": 5,
        "goals_against": 5,
        "goal_difference": 0,
        "position": 2
      },
      {
        "team_id": "47",
        "team": "Ghana",
        "fifa_code": "GHA",
        "flag": "https://flagcdn.com/w80/gh.png",
        "played": 3,
        "wins": 1,
        "draws": 1,
        "losses": 1,
        "points": 4,
        "goals_for": 2,
        "goals_against": 2,
        "goal_difference": 0,
        "position": 3
      },
      {
        "team_id": "48",
        "team": "Panama",
        "fifa_code": "PAN",
        "flag": "https://flagcdn.com/w80/pa.png",
        "played": 3,
        "wins": 0,
        "draws": 0,
        "losses": 3,
        "points": 0,
        "goals_for": 0,
        "goals_against": 4,
        "goal_difference": -4,
        "position": 4
      }
    ]
  }
}